django_safemigrate/__init__.py
django_safemigrate/apps.py
django_safemigrate/check.py
django_safemigrate/models.py
django_safemigrate/management/__init__.py
django_safemigrate/management/commands/__init__.py
django_safemigrate/management/commands/safemigrate.py
django_safemigrate/migrations/0001_initial.py
django_safemigrate/migrations/__init__.py
django_safemigrate-6.0.dist-info/METADATA
django_safemigrate-6.0.dist-info/WHEEL
django_safemigrate-6.0.dist-info/entry_points.txt
django_safemigrate-6.0.dist-info/licenses/LICENSE
django_safemigrate-6.0.dist-info/RECORD
