Metadata-Version: 2.4
Name: django-safemigrate
Version: 6.0
Summary: Safely run migrations before deployment
Project-URL: homepage, https://github.com/ryanhiebert/django-safemigrate
Project-URL: source, https://github.com/ryanhiebert/django-safemigrate
Project-URL: history, https://github.com/ryanhiebert/django-safemigrate/blob/main/HISTORY.rst
Project-URL: issues, https://github.com/ryanhiebert/django-safemigrate/issues
Author-email: Ryan Hiebert <ryan@ryanhiebert.com>
License: MIT
License-File: LICENSE
Requires-Python: >=3.9
Requires-Dist: django>=4.2
